<DOMSymbolItem xmlns:xsi="http://www.w3.org/2001/XMLSchema-instance" xmlns="http://ns.adobe.com/xfl/2008/" name="cloth 2" itemID="56c22a6a-00000252" lastModified="1455565418">
  <timeline>
    <DOMTimeline name="cloth 2">
      <layers>
        <DOMLayer name="Layer 1" color="#4FFF4F" current="true" isSelected="true">
          <frames>
            <DOMFrame index="0" keyMode="9728">
              <elements>
                <DOMShape>
                  <fills>
                    <FillStyle index="1">
                      <SolidColor color="#FFFFFF" alpha="0.96078431372549"/>
                    </FillStyle>
                    <FillStyle index="2">
                      <SolidColor color="#CCCCCC" alpha="0.96078431372549"/>
                    </FillStyle>
                  </fills>
                  <edges>
                    <Edge fillStyle0="1" fillStyle1="2" edges="!4904 435S3[4283 668 3872 971!3872 971[3585 1183 3274 1542!3274 1542[2949 1925 2780 2115!2780 2115[2569 2353 2381 2535!2381 2535[2317 2629 2252 2702!2252 2702|2252 2703!2252 2703[2252 2731 2248 2750!2248 2750[2246 2776 2226 2796!2226
 2796|2226 2797!2226 2797[2226 2810 2214 2828!2214 2828[2202 2845 2191 2847!2191 2847|2190 2847!2190 2847|2191 2848!2191 2848[2200 2870 2209 2889!2209 2889[2213 2901 2213 2923!2213 2923[2213 2951 2209 2957!2209 2957[2200 2973 2160 2978
!2160 2978[2200 3251 2258 3434!2258 3434[2263 3449 2268 3464!2268 3464[2358 3734 2526 3945!2526 3945[2533 3954 2540 3963!2540 3963[2627 4069 2832 4252!2832 4252[3062 4456 3074 4469!3074 4469[3256 4661 3599 4756!3599 4756[3682 4779 3808
 4807!3808 4807[3893 4829 3893 4849!3893 4849[3893 4881 3875 4888!3875 4888[3803 4846 3459 4721!3459 4721[3173 4618 3074 4518!3074 4518[2916 4354 2833 4274!2833 4274[2700 4144 2567 4043!2567 4043[2560 4037 2553 4032!2553 4032[2426 3936
 2280 3579!2280 3579[2214 3420 2180 3296!2180 3296[2139 3153 2139 3057!2139 3057[2139 3010 2140 2998!2140 2998[2141 2989 2142 2981!2142 2981[2132 2983 2123 2985!2123 2985[2113 2986 2104 2988!2104 2988[2105 2996 2106 3005!2106 3005[2117
 3083 2123 3196!2123 3196[2124 3231 2125 3270!2125 3270[2127 3338 2127 3416!2127 3416[2153 3694 2323 3873!2323 3873[2371 3957 2522 4091!2522 4091[2559 4124 2597 4156!2597 4156[2601 4159 2606 4163!2606 4163[2700 4241 2807 4316!2807 4316
[2892 4376 3015 4510!3015 4510[3030 4526 3044 4541!3044 4541[3179 4688 3239 4743!3239 4743[3239 4747 3236 4750!3236 4750[3250 4766 3266 4785!3266 4785[3288 4806 3309 4831!3309 4831[3373 4905 3493 5050!3493 5050[3491 5057 3488 5060!3488
 5060[3487 5061 3486 5062!3486 5062[3530 5120 3530 5126!3530 5126[3530 5140 3510 5166!3510 5166[3487 5195 3466 5195!3466 5195[3456 5195 3429 5161!3429 5161[3401 5125 3394 5118!3394 5118|3389 5118!3389 5118[3392 5125 3400 5142!3400 5142
[3407 5159 3410 5171!3410 5171[3404 5184 3392 5188!3392 5188[3297 5096 3127 4827!3127 4827[3073 4742 3037 4682!3037 4682[2994 4634 2934 4561!2934 4561[2751 4340 2700 4320!2700 4320[2651 4301 2594 4260!2594 4260[2525 4211 2443 4132!2443
 4132[2282 3975 2282 3888!2282 3888[2282 3886 2282 3885!2282 3885[2216 3768 2182 3706!2182 3706[2111 3578 2095 3492!2095 3492[2079 3403 2077 3232!2077 3232[2078 3160 2079 3118!2079 3118[2079 3073 2079 3063!2079 3063[2079 3062 2079 3061
!2079 3061[2080 3042 2081 3025!2081 3025[2081 3007 2082 2992!2082 2992[2080 2992 2079 2993!2079 2993[2071 2994 2064 2995!2064 2995[2064 2996 2064 2997!2064 2997[2064 3002 2050 3050!2050 3050[2051 3073 2051 3098!2051 3098[2051 3155 2036
 3220!2036 3220[2028 3286 2012 3388!2012 3388[1983 3718 1875 3994!1875 3994[1859 4034 1841 4073!1841 4073[1613 4581 1063 4995!1063 4995|1054 4989!1054 4989[1645 4448 1836 3995!1836 3995[1842 3982 1847 3968!1847 3968[1882 3882 1907 3790
!1907 3790[1893 3818 1878 3838!1878 3838[1871 3850 1871 3828!1871 3828[1871 3826 1872 3824!1872 3824[1877 3801 1919 3701!1919 3701[1928 3679 1936 3659!1936 3659[1938 3655 1939 3651!1939 3651[1949 3597 1957 3541!1957 3541[1974 3413 1980
 3237!1980 3237[1974 3236 1974 3223!1974 3223[1974 3200 1980 3141!1980 3141[1980 3137 1981 3133!1981 3133[1982 3119 1983 3107!1983 3107[1983 3075 1983 3042!1983 3042|1984 3007!1984 3007[1977 3007 1971 3008!1971 3008[1964 3009 1959 3009
!1959 3009[1959 3010 1959 3011!1959 3011[1963 3026 1963 3081!1963 3081[1963 3088 1963 3097!1963 3097[1963 3112 1962 3128!1962 3128[1958 3197 1936 3286!1936 3286[1910 3390 1859 3523!1859 3523[1848 3552 1837 3580!1837 3580[1820 3619 1804
 3657!1804 3657[1740 3802 1674 3908!1674 3908[1669 3916 1664 3925!1664 3925[1560 4080 1271 4306!1271 4306[1164 4390 987 4520!987 4520[879 4599 745 4695!745 4695[732 4711 732 4689!732 4689[732 4671 968 4486!968 4486[1035 4432 1122 4365
!1122 4365[1500 4073 1619 3924!1619 3924[1633 3907 1643 3891!1643 3891[1678 3838 1714 3766!1714 3766[1768 3660 1824 3512!1824 3512[1843 3461 1859 3415!1859 3415[1928 3210 1928 3092!1928 3092[1928 3072 1921 3041!1921 3041[1920 3038 1920
 3035!1920 3035[1914 3015 1908 3000!1908 3000[1905 2998 1903 2997!1903 2997[1907 3009 1911 3024!1911 3024[1905 3035 1893 3042!1893 3042[1882 3036 1871 3036!1871 3036[1872 3022 1867 2997!1867 2997[1864 2982 1863 2971!1863 2971[1860 2968
 1860 2967!1860 2967[1860 2964 1862 2959!1862 2959[1862 2958 1862 2957!1862 2957|1863 2956!1863 2956[1867 2947 1876 2935!1876 2935[1875 2933 1874 2931!1874 2931[1844 2875 1844 2850!1844 2850[1844 2835 1861 2818!1861 2818[1862 2817 1863
 2816!1863 2816[1853 2810 1850 2809!1850 2809|1851 2806!1851 2806[1855 2805 1870 2811!1870 2811[1872 2810 1874 2809!1874 2809|1874 2807!1874 2807[1879 2806 1885 2806!1885 2806[1885 2805 1885 2804!1885 2804[1883 2804 1882 2804!1882 2804
[1868 2790 1862 2774!1862 2774[1862 2773 1862 2772!1862 2772|1857 2773!1857 2773[1853 2767 1853 2756!1853 2756[1852 2747 1852 2740!1852 2740|1851 2740!1851 2740[1848 2745 1848 2735!1848 2735[1848 2723 1863 2703!1863 2703[1873 2689 1886
 2678!1886 2678[1886 2668 1886 2662!1886 2662[1886 2630 1902 2611!1902 2611[1869 2519 1821 2343!1821 2343[1768 2148 1727 2045!1727 2045[1589 1694 1262 1452!1262 1452[1145 1349 1086 1299!1086 1299[981 1210 842 1156!842 1156[727 1111 613
 1027!613 1027[500 943 462 875!462 875[350 681 295 585!295 585[196 413 140 284!140 284|153 281!153 281[250 392 343 577!343 577[452 797 506 873!506 873[538 919 614 971!614 971[641 988 673 1007!673 1007[739 1046 856 1102!856 1102[900 1123
 951 1147!951 1147[1026 1182 1130 1289!1130 1289[1245 1408 1301 1443!1301 1443[1579 1615 1760 2057!1760 2057[1821 2205 1872 2389!1872 2389[1897 2477 1926 2594!1926 2594[1937 2590 1950 2591!1950 2591[1955 2591 1960 2592!1960 2592[1955
 2573 1952 2558!1952 2558[1945 2529 1942 2513!1942 2513[1940 2502 1940 2496!1940 2496[1940 2430 1940 2428!1940 2428[1945 2383 1968 2374!1968 2374[1971 2381 1973 2388!1973 2388[1978 2403 1983 2416!1983 2416[2001 2471 2004 2481!2004 2481
[2007 2493 2008 2516!2008 2516[2016 2532 2028 2555!2028 2555[2055 2608 2061 2631!2061 2631[2066 2632 2072 2634!2072 2634[2099 2643 2137 2653!2137 2653[2152 2608 2167 2569!2167 2569[2199 2484 2223 2430!2223 2430[2300 2261 2419 2160!2419
 2160[2598 2008 2697 1872!2697 1872[2784 1753 2846 1590!2846 1590[2892 1471 3024 1314!3024 1314[3036 1300 3275 1036!3275 1036[3429 867 3499 753!3499 753[3595 595 3594 459!3594 459|3607 457!3607 457|3611 463!3611 463|3611 496!3611 496
[3611 629 3518 782!3518 782[3451 893 3302 1058!3302 1058[3070 1317 3056 1334!3056 1334[2925 1492 2873 1616!2873 1616[2821 1740 2706 1894!2706 1894[2655 1961 2485 2165!2485 2165[2271 2420 2185 2601!2185 2601[2170 2631 2160 2660!2160 2660
[2194 2669 2216 2678!2216 2678|2217 2679!2217 2679[2219 2676 2220 2674!2220 2674[2257 2619 2325 2524!2325 2524[2335 2509 2346 2494!2346 2494[2515 2257 2606 2146!2606 2146[2701 2030 2984 1701!2984 1701[3041 1634 3105 1559!3105 1559[3296
 1337 3647 1040!3647 1040[3691 1002 3737 964!3737 964[3857 865 4068 699!4068 699[4233 570 4453 401!4453 401[4450 398 4448 396!4448 396[4458 390 4468 389!4468 389[4469 388 4470 387!4470 387[4472 388 4474 389!4474 389[4492 388 4510 402
!4510 402[4529 404 4627 408!4627 408[4650 409 4678 410!4678 410[4805 417 4868 433!4868 433[4882 428 4896 423!4896 423|4904 435"/>
                    <Edge fillStyle1="1" edges="
!5119 265S2[5119 359 4696 543!4696 543[4360 688 4343 696!4343 696[4147 787 4052 856!4052 856[3823 1024 3658 1177!3658 1177[3548 1280 3324 1516!3324 1516[3260 1585 3052 1838!3052 1838[2881 2048 2739 2180!2739 2180[2637 2275 2479 2569!2479
 2569[2344 2821 2294 2826!2294 2826[2296 2840 2296 2873!2296 2873[2296 2932 2258 2964!2258 2964[2219 2995 2219 3027!2219 3027[2219 3225 2401 3566!2401 3566[2526 3803 2708 4056!2708 4056[2798 4183 2972 4298!2972 4298[3111 4389 3403 4534
!3403 4534[3642 4653 3918 4772!3918 4772[4003 4818 4038 4864!4038 4864[4076 4915 4076 4992!4076 4992[4076 5139 3844 5273!3844 5273[3589 5419 3243 5419!3243 5419[3205 5419 3091 5449!3091 5449[2966 5481 2923 5485!2923 5485|1355 5485!1355
 5485[765 5398 633 5290!633 5290[508 5187 480 5139!480 5139[456 5098 456 5004!456 5004[456 4938 487 4876!487 4876[501 4848 519 4829!519 4829|519 4828!519 4828[519 4760 868 4465!868 4465[1165 4215 1229 4176!1229 4176[1380 4072 1451 4020
!1451 4020[1535 3958 1593 3908!1593 3908[1585 3900 1580 3888!1580 3888[1571 3848 1571 3847!1571 3847[1571 3827 1612 3748!1612 3748[1674 3628 1702 3566!1702 3566[1832 3271 1832 2976!1832 2976[1806 2824 1806 2799!1806 2799[1806 2783 1820
 2711!1820 2711[1834 2643 1834 2641!1834 2641[1834 2624 1748 2368!1748 2368[1657 2095 1639 1987!1639 1987[1620 1861 1408 1673!1408 1673[1150 1462 1049 1356!1049 1356[1005 1311 809 1229!809 1229[598 1141 554 1108!554 1108[466 1042 412
 948!412 948[360 840 329 786!329 786[227 630 150 496!150 496[0 235 0 142!0 142[0 76 15 59!15 59[47 22 179 2!179 2|3686 2!3686 2|3583 1!3583 1|3664 0!3664 0[3832 14 3988 39!3988 39[4086 55 4376 102!4376 102[4580 133 4901 163!4901 163[5119
 194 5119 265"/>
                    <Edge fillStyle0="1" fillStyle1="2" edges="
!2630 340S3[2636 309 2643 308!2643 308[2645 320 2647 343!2647 343[2655 303 2688 296!2688 296|2689 293!2689 293[2693 288 2700 284!2700 284[2708 288 2712 294!2712 294[2717 294 2723 295!2723 295[2725 291 2727 287!2727 287[2733 278 2748 268
!2748 268[2755 281 2762 323!2762 323[2767 354 2768 371!2768 371[2777 421 2777 486!2777 486[2777 784 2675 1034!2675 1034[2624 1156 2449 1445!2449 1445[2397 1530 2356 1609!2356 1609[2344 1637 2338 1658!2338 1658[2338 1665 2331 1669!2331
 1669[2328 1667 2327 1666!2327 1666[2261 1796 2224 1909!2224 1909[2136 2171 2123 2500!2123 2500[2121 2555 2121 2611!2121 2611[2121 2633 2117 2637!2117 2637|2108 2640!2108 2640[2093 2579 2093 2478!2093 2478[2093 2470 2093 2461!2093 2461
[2094 2299 2121 2154!2121 2154[2120 2136 2120 2113!2120 2113[2120 2093 2121 2075!2121 2075[2121 2072 2122 2068!2122 2068[2126 2002 2143 1957!2143 1957[2148 1944 2159 1923!2159 1923[2161 1916 2163 1908!2163 1908[2181 1849 2196 1808!2196
 1808[2212 1737 2306 1579!2306 1579[2315 1563 2324 1549!2324 1549[2346 1499 2362 1462!2362 1462[2404 1368 2436 1316!2436 1316[2497 1183 2522 1123!2522 1123[2621 882 2631 730!2631 730[2625 538 2625 380!2625 380[2625 365 2630 340!1870 626
[1958 823 1959 1001!1959 1001[1970 1063 1983 1141!1983 1141[1983 1188 1976 1224!1976 1224|1968 1224!1968 1224[1948 1109 1935 1029!1935 1029[1918 925 1913 866!1913 866[1887 759 1838 638!1838 638[1770 473 1639 240!1639 240|1652 238!1652
 238[1813 498 1870 626!2001 1127[2004 1247 2001 1377!2001 1377|1994 1377!1994 1377[1992 1354 1992 1332!1992 1332|1994 1127!1994 1127|2001 1127!1706 1531[1683 1492 1601 1410!1601 1410[1507 1316 1490 1294!1490 1294[1439 1231 1282 1061!1282
 1061[1148 915 1089 832!1089 832[965 658 914 598!914 598[808 473 681 384!681 384[793 426 917 553!917 553[1018 657 1095 781!1095 781[1141 837 1286 999!1286 999[1423 1151 1481 1224!1481 1224[1541 1298 1665 1451!1665 1451[1767 1584 1803
 1683!1803 1683[1832 1759 1895 1914!1895 1914[1944 2050 1944 2142!1944 2142[1944 2153 1953 2175!1953 2175[1961 2196 1961 2208!1961 2208[1961 2215 1958 2254!1958 2254|1950 2254!1950 2254[1934 2159 1887 2011!1887 2011[1833 1846 1810 1774
!1810 1774[1770 1643 1706 1531!2007 2610[2005 2605 2004 2601!2004 2601[2003 2603 2002 2607!2002 2607[2004 2608 2007 2610!2022 2692|2023 2693!2023 2693[2051 2716 2054 2721!2054 2721[2053 2725 2047 2727!2047 2727[2026 2721 2011 2708!2011
 2708[2008 2706 2006 2704!2006 2704[2000 2708 1992 2714!1992 2714[1996 2718 2003 2723!2003 2723[2023 2740 2024 2744!2024 2744[2023 2746 2024 2749!2024 2749[2023 2751 2017 2751!2017 2751[2007 2751 2001 2745!2001 2745[1994 2738 1983 2738
!1983 2738[1979 2738 1977 2741!1977 2741[1981 2743 1986 2745!1986 2745[2017 2760 2061 2784!2061 2784[2074 2791 2088 2799!2088 2799|2090 2806!2090 2806[2087 2811 2082 2812!2082 2812|2073 2812!2073 2812|2105 2817!2105 2817|2108 2823!2108
 2823[2107 2824 2107 2825!2107 2825[2116 2823 2129 2819!2129 2819|2130 2818!2130 2818[2140 2814 2148 2815!2148 2815|2113 2831!2113 2831[2105 2830 2103 2828!2103 2828[2097 2830 2089 2830!2089 2830[2072 2830 2057 2829!2057 2829[2025 2826
 1999 2818!1999 2818[1987 2826 1968 2826!1968 2826[1962 2826 1956 2825!1956 2825[1990 2840 2000 2852!2000 2852[1998 2858 1995 2861!1995 2861[1972 2845 1950 2834!1950 2834[1945 2832 1942 2830!1942 2830[1938 2828 1936 2827!1936 2827[1934
 2835 1933 2842!1933 2842[1937 2843 1941 2846!1941 2846[1944 2847 1947 2849!1947 2849[1948 2849 1949 2850!1949 2850[1951 2851 1954 2853!1954 2853[1964 2860 1982 2871!1982 2871[1982 2874 1972 2874!1972 2874[1969 2874 1956 2867!1956 2867
[1952 2865 1948 2862!1948 2862[1946 2861 1944 2860!1944 2860[1942 2859 1940 2858!1940 2858[1944 2864 1947 2872!1947 2872[1949 2876 1951 2881!1951 2881[1955 2892 1962 2901!1962 2901|1964 2901!1964 2901[2017 2898 2049 2895!2049 2895|2050
 2895!2050 2895[2057 2895 2102 2905!2102 2905[2111 2906 2123 2909!2123 2909[2121 2914 2117 2915!2117 2915|2025 2915!2025 2915[1983 2914 1970 2913!1970 2913[1995 2942 2042 2953!2042 2953[2047 2954 2053 2955!2053 2955|2055 2964!2055 2964
[2068 2961 2084 2960!2084 2960[2103 2958 2127 2958!2127 2958[2134 2958 2140 2958!2140 2958[2146 2958 2151 2958!2151 2958[2153 2955 2156 2953!2156 2953[2156 2955 2157 2957!2157 2957[2181 2956 2189 2951!2189 2951[2197 2947 2197 2932!2197
 2932[2197 2903 2189 2891!2189 2891[2185 2884 2178 2880!2178 2880[2162 2869 2134 2869!2134 2869[2123 2872 2115 2874!2115 2874[2098 2878 2091 2878!2091 2878[2067 2878 2052 2876!2052 2876[2022 2871 2022 2859!2022 2859[2022 2853 2024 2851
!2024 2851[2026 2850 2030 2850!2030 2850[2043 2850 2055 2849!2055 2849[2097 2846 2126 2837!2126 2837[2152 2828 2167 2815!2167 2815[2175 2808 2183 2803!2183 2803[2178 2803 2174 2803!2174 2803|2161 2801!2161 2801[2155 2798 2154 2795!2154
 2795[2174 2791 2189 2786!2189 2786[2189 2783 2189 2781!2189 2781[2185 2781 2179 2783!2179 2783[2171 2782 2168 2778!2168 2778[2177 2776 2182 2772!2182 2772[2185 2769 2188 2768!2188 2768[2187 2765 2188 2763!2188 2763[2182 2761 2181 2760
!2181 2760[2179 2759 2178 2750!2178 2750[2174 2748 2171 2746!2171 2746[2170 2748 2163 2748!2163 2748[2155 2748 2148 2747!2148 2747[2114 2744 2089 2724!2089 2724[2084 2718 2079 2714!2079 2714[2076 2716 2073 2718!2073 2718[2075 2720 2076
 2723!2076 2723[2079 2728 2069 2728!2069 2728[2067 2728 2066 2728!2066 2728[2063 2726 2061 2725!2061 2725[2058 2726 2057 2726!2057 2726[2055 2724 2055 2721!2055 2721[2046 2712 2034 2696!2034 2696[2033 2695 2033 2694!2033 2694[2028 2692
 2023 2691!2023 2691[2022 2691 2022 2692!1889 2955[1887 2956 1887 2957!1887 2957[1888 2957 1891 2958!1891 2958[1889 2956 1889 2955!2161 2846[2148 2849 2145 2852!2145 2852|2143 2854!2143 2854[2162 2852 2162 2846!2162 2846|2161 2846"/>
                    <Edge fillStyle1="2" edges="
!3115 4647S2[3111 4644 3109 4642!3109 4642[3110 4645 3111 4648!3111 4648[3112 4647 3115 4647"/>
                    <Edge fillStyle0="1" fillStyle1="2" edges="
!2193 4185S3|2193 4187!2193 4187|2202 4185!2202 4185[2249 4591 2840 5118!2840 5118|2836 5125!2836 5125[2563 4914 2386 4671!2386 4671[2192 4404 2192 4200!2192 4200[2192 4186 2193 4185!2001 3976[2001 3982 2002 3989!2002 3989[2002 3987 2003
 3985!2003 3985[2009 3994 2011 4003!2011 4003[2012 4009 2012 4027!2012 4027[2012 4033 2007 4068!2007 4068[2007 4069 2007 4071!2007 4071[2007 4073 2007 4076!2007 4076[2007 4221 1983 4327!1983 4327[1958 4435 1958 4489!1958 4489[1958 4522
 1932 4634!1932 4634[1923 4781 1860 4973!1860 4973[1796 5167 1700 5337!1700 5337|1689 5333!1689 5333[1720 5258 1738 5188!1738 5188|1733 5177!1733 5177|1716 5175!1716 5175|1716 5195!1716 5195[1709 5202 1700 5204!1700 5204[1690 5197 1678
 5195!1678 5195[1672 5194 1651 5174!1651 5174[1575 5274 1486 5358!1486 5358[1467 5375 1448 5392!1448 5392|1437 5386!1437 5386[1440 5381 1460 5355!1460 5355[1501 5300 1612 5155!1612 5155[1610 5155 1607 5155!1607 5155[1599 5168 1599 5145
!1599 5145[1599 5130 1705 4921!1705 4921[1823 4686 1862 4559!1862 4559[1891 4466 1933 4263!1933 4263[1961 4130 1984 4047!1984 4047[1985 4044 1986 4041!1986 4041[1990 4006 1994 3976!1994 3976|2001 3976"/>
                    <Edge cubics="!1851 2740(;1851,2740 1848,2745 1848,2735q1851 2740Q1848 2745q1848 2735);"/>
                    <Edge cubics="!1862 2772(;1862,2772 1857,2773 1857,2773q1862 2772 1857 2773);"/>
                    <Edge cubics="!1857 2773(;1855,2770 1853,2766 1853,2756q1857 2773Q1853 2767q1853 2756);"/>
                    <Edge cubics="!1850 2809(;1850,2809 1851,2806 1851,2806q1850 2809 1851 2806);"/>
                    <Edge cubics="!2076 2723(;2076,2723 2079,2728 2069,2728q2076 2723Q2079 2728q2069 2728);"/>
                    <Edge cubics="!2179 2783(;2179,2783 2171,2782 2168,2778q2179 2783Q2171 2782q2168 2778);"/>
                    <Edge cubics="!2148 2815(;2143,2818 2117,2830 2113,2831q2148 2815 2113 2831);"/>
                    <Edge cubics="!1982 2871(;1982,2871 1982,2874 1972,2874q1982 2871Q1982 2874q1972 2874);"/>
                    <Edge cubics="!2000 2852(;1999,2855 1998,2858 1995,2861q2000 2852Q1998 2858q1995 2861);"/>
                    <Edge cubics="!2174 2803(;2164,2803 2161,2801 2161,2801q2174 2803Q2161 2801q2161 2801);"/>
                    <Edge cubics="!2161 2801(;2161,2800 2155,2798 2154,2795q2161 2801Q2155 2798q2154 2795);"/>
                    <Edge cubics="!2022 2859(;2022,2849 2025,2851 2030,2850q2022 2859Q2022 2853q2024 2851Q2026 2850q2030 2850);"/>
                    <Edge cubics="!2161 2846(;2157,2847 2148,2849 2145,2852q2161 2846Q2148 2849q2145 2852);"/>
                    <Edge cubics="!2145 2852(;2145,2852 2143,2854 2143,2854q2145 2852 2143 2854);"/>
                    <Edge cubics="!2143 2854(;2153,2853 2162,2849 2162,2846q2143 2854Q2162 2852q2162 2846);"/>
                    <Edge cubics="!2162 2846(;2162,2846 2161,2846 2161,2846q2162 2846 2161 2846);"/>
                    <Edge cubics="!2088 2799(;2088,2799 2090,2806 2090,2806q2088 2799 2090 2806);"/>
                    <Edge cubics="!2090 2806(;2088,2809 2087,2811 2082,2812q2090 2806Q2087 2811q2082 2812);"/>
                    <Edge cubics="!2082 2812(;2082,2812 2073,2812 2073,2812q2082 2812 2073 2812);"/>
                    <Edge cubics="!2073 2812(;2073,2812 2100,2815 2105,2817q2073 2812Q2073 2812q2105 2817);"/>
                    <Edge cubics="!2105 2817(;2105,2817 2108,2823 2108,2823q2105 2817 2108 2823);"/>
                    <Edge cubics="!2054 2721(;2054,2721 2053,2725 2047,2727q2054 2721Q2053 2725q2047 2727);"/>
                    <Edge cubics="!2024 2744(;2022,2748 2027,2751 2017,2751q2024 2744Q2023 2746q2024 2749Q2023 2751q2017 2751);"/>
                    <Edge cubics="!2017 2751(;1997,2751 2005,2738 1983,2738q2017 2751Q2007 2751q2001 2745Q1994 2738q1983 2738);"/>
                    <Edge cubics="!2123 2909(;2122,2912 2121,2914 2117,2915q2123 2909Q2121 2914q2117 2915);"/>
                    <Edge cubics="!2117 2915(;2117,2915 2025,2915 2025,2915q2117 2915 2025 2915);"/>
                    <Edge cubics="!1886 2678(;1886,2671 1886,2666 1886,2662q1886 2678Q1886 2668q1886 2662);"/>
                    <Edge cubics="!1863 2703(;1870,2694 1877,2685 1886,2678q1863 2703Q1873 2689q1886 2678);"/>
                    <Edge cubics="!1852 2740(;1851,2740 1851,2740 1851,2740q1852 2740Q1851 2740q1851 2740);"/>
                    <Edge cubics="!1862 2774(;1862,2773 1862,2773 1862,2772q1862 2774Q1862 2773q1862 2772);"/>
                    <Edge cubics="!1853 2756(;1852,2750 1852,2745 1852,2740q1853 2756Q1852 2747q1852 2740);"/>
                    <Edge cubics="!1848 2735(;1848,2727 1853,2716 1863,2703q1848 2735Q1848 2723q1863 2703);"/>
                    <Edge cubics="!1885 2804(;1884,2804 1883,2804 1882,2804q1885 2804Q1883 2804q1882 2804);"/>
                    <Edge cubics="!1861 2818(;1862,2817 1862,2817 1863,2816q1861 2818Q1862 2817q1863 2816);"/>
                    <Edge cubics="!1863 2816(;1856,2812 1852,2810 1850,2809q1863 2816Q1853 2810q1850 2809);"/>
                    <Edge cubics="!1874 2809(;1874,2809 1874,2807 1874,2807q1874 2809 1874 2807);"/>
                    <Edge cubics="!1870 2811(;1871,2810 1873,2810 1874,2809q1870 2811Q1872 2810q1874 2809);"/>
                    <Edge cubics="!1851 2806(;1854,2805 1860,2807 1870,2811q1851 2806Q1855 2805q1870 2811);"/>
                    <Edge cubics="!1844 2850(;1844,2840 1850,2829 1861,2818q1844 2850Q1844 2835q1861 2818);"/>
                    <Edge cubics="!1882 2804(;1873,2795 1866,2785 1862,2774q1882 2804Q1868 2790q1862 2774);"/>
                    <Edge cubics="!2089 2724(;2086,2720 2082,2717 2079,2714q2089 2724Q2084 2718q2079 2714);"/>
                    <Edge cubics="!2079 2714(;2077,2715 2075,2717 2073,2718q2079 2714Q2076 2716q2073 2718);"/>
                    <Edge cubics="!2061 2725(;2059,2726 2058,2726 2057,2726q2061 2725Q2058 2726q2057 2726);"/>
                    <Edge cubics="!2073 2718(;2074,2719 2075,2721 2076,2723q2073 2718Q2075 2720q2076 2723);"/>
                    <Edge cubics="!2057 2726(;2056,2725 2055,2723 2055,2721q2057 2726Q2055 2724q2055 2721);"/>
                    <Edge cubics="!1983 2738(;1980,2738 1978,2739 1977,2741q1983 2738Q1979 2738q1977 2741);"/>
                    <Edge cubics="!1977 2741(;1980,2742 1983,2744 1986,2745q1977 2741Q1981 2743q1986 2745);"/>
                    <Edge cubics="!1968 2826(;1964,2826 1960,2826 1956,2825q1968 2826Q1962 2826q1956 2825);"/>
                    <Edge cubics="!1956 2825(;1979,2835 1993,2844 2000,2852q1956 2825Q1990 2840q2000 2852);"/>
                    <Edge cubics="!1999 2818(;1991,2823 1981,2826 1968,2826q1999 2818Q1987 2826q1968 2826);"/>
                    <Edge cubics="!1995 2861(;1980,2850 1965,2841 1950,2834q1995 2861Q1972 2845q1950 2834);"/>
                    <Edge cubics="!2113 2831(;2108,2830 2104,2829 2103,2828q2113 2831Q2105 2830q2103 2828);"/>
                    <Edge cubics="!2108 2823(;2107,2824 2107,2824 2107,2825q2108 2823Q2107 2824q2107 2825);"/>
                    <Edge cubics="!2103 2828(;2099,2829 2094,2830 2089,2830q2103 2828Q2097 2830q2089 2830);"/>
                    <Edge cubics="!2055 2721(;2049,2715 2042,2707 2034,2696q2055 2721Q2046 2712q2034 2696);"/>
                    <Edge cubics="!2171 2746(;2170,2747 2168,2748 2163,2748q2171 2746Q2170 2748q2163 2748);"/>
                    <Edge cubics="!2183 2803(;2180,2803 2177,2803 2174,2803q2183 2803Q2178 2803q2174 2803);"/>
                    <Edge cubics="!2167 2815(;2172,2810 2178,2806 2183,2803q2167 2815Q2175 2808q2183 2803);"/>
                    <Edge cubics="!2130 2818(;2137,2815 2143,2814 2148,2815q2130 2818Q2140 2814q2148 2815);"/>
                    <Edge cubics="!1876 2935(;1875,2934 1875,2932 1874,2931q1876 2935Q1875 2933q1874 2931);"/>
                    <Edge cubics="!1891 2958(;1890,2957 1889,2956 1889,2955q1891 2958Q1889 2956q1889 2955);"/>
                    <Edge cubics="!1874 2931(;1854,2894 1844,2867 1844,2850q1874 2931Q1844 2875q1844 2850);"/>
                    <Edge cubics="!153 281(;327,479 368,676 506,873q153 281Q250 392q343 577Q452 797q506 873);"/>
                    <Edge cubics="!951 1147(;1089,1211 1173,1364 1301,1443q951 1147Q1026 1182q1130 1289Q1245 1408q1301 1443);"/>
                    <Edge cubics="!1262 1452(;1124,1350 1071,1245 842,1156q1262 1452Q1145 1349q1086 1299Q981 1210q842 1156);"/>
                    <Edge cubics="!842 1156(;687,1096 512,965 462,875q842 1156Q727 1111q613 1027Q500 943q462 875);"/>
                    <Edge cubics="!462 875(;353,676 233,498 140,284q462 875Q350 681q295 585Q196 413q140 284);"/>
                    <Edge cubics="!140 284(;140,284 153,281 153,281q140 284 153 281);"/>
                    <Edge cubics="!1760 2057(;1801,2156 1838,2266 1872,2389q1760 2057Q1821 2205q1872 2389);"/>
                    <Edge cubics="!1886 2662(;1886,2641 1891,2624 1902,2611q1886 2662Q1886 2630q1902 2611);"/>
                    <Edge cubics="!2252 2702(;2252,2702 2252,2702 2252,2703q2252 2702Q2252 2702q2252 2703);"/>
                    <Edge cubics="!2216 2678(;2216,2678 2216,2678 2217,2679q2216 2678Q2216 2678q2217 2679);"/>
                    <Edge cubics="!2181 2760(;2180,2759 2179,2756 2178,2750q2181 2760Q2179 2759q2178 2750);"/>
                    <Edge cubics="!2178 2750(;2175,2749 2173,2747 2171,2746q2178 2750Q2174 2748q2171 2746);"/>
                    <Edge cubics="!1872 2389(;1889,2448 1907,2516 1926,2594q1872 2389Q1897 2477q1926 2594);"/>
                    <Edge cubics="!1902 2611(;1880,2550 1853,2460 1821,2343q1902 2611Q1869 2519q1821 2343);"/>
                    <Edge cubics="!1301 1443(;1486,1558 1639,1762 1760,2057q1301 1443Q1579 1615q1760 2057);"/>
                    <Edge cubics="!1821 2343(;1786,2213 1754,2114 1727,2045q1821 2343Q1768 2148q1727 2045);"/>
                    <Edge cubics="!1727 2045(;1635,1811 1480,1613 1262,1452q1727 2045Q1589 1694q1262 1452);"/>
                    <Edge cubics="!2346 2494(;2459,2336 2545,2220 2606,2146q2346 2494Q2515 2257q2606 2146);"/>
                    <Edge cubics="!1911 3024(;1908,3030 1904,3036 1893,3042q1911 3024Q1905 3035q1893 3042);"/>
                    <Edge cubics="!1893 3042(;1893,3042 1882,3036 1871,3036q1893 3042Q1882 3036q1871 3036);"/>
                    <Edge cubics="!745 4695(;745,4695 732,4711 732,4689q745 4695Q732 4711q732 4689);"/>
                    <Edge cubics="!2540 3963(;2687,4142 2994,4385 3074,4469q2540 3963Q2627 4069q2832 4252Q3062 4456q3074 4469);"/>
                    <Edge cubics="!3074 4469(;3383,4794 3893,4783 3893,4849q3074 4469Q3256 4661q3599 4756Q3682 4779q3808 4807Q3893 4829q3893 4849);"/>
                    <Edge cubics="!3893 4849(;3893,4872 3885,4884 3875,4888q3893 4849Q3893 4881q3875 4888);"/>
                    <Edge cubics="!3875 4888(;3660,4762 3247,4693 3074,4518q3875 4888Q3803 4846q3459 4721Q3173 4618q3074 4518);"/>
                    <Edge cubics="!2213 2923(;2213,2942 2212,2953 2209,2957q2213 2923Q2213 2951q2209 2957);"/>
                    <Edge cubics="!2189 2951(;2194,2948 2197,2942 2197,2932q2189 2951Q2197 2947q2197 2932);"/>
                    <Edge cubics="!2151 2958(;2152,2956 2154,2954 2156,2953q2151 2958Q2153 2955q2156 2953);"/>
                    <Edge cubics="!2157 2957(;2173,2956 2184,2954 2189,2951q2157 2957Q2181 2956q2189 2951);"/>
                    <Edge cubics="!2156 2953(;2156,2954 2156,2956 2157,2957q2156 2953Q2156 2955q2157 2957);"/>
                    <Edge cubics="!2209 2957(;2203,2968 2187,2975 2160,2978q2209 2957Q2200 2973q2160 2978);"/>
                    <Edge cubics="!2140 2998(;2141,2992 2141,2986 2142,2981q2140 2998Q2141 2989q2142 2981);"/>
                    <Edge cubics="!1959 3009(;1959,3010 1959,3010 1959,3011q1959 3009Q1959 3010q1959 3011);"/>
                    <Edge cubics="!2139 3057(;2139,3026 2139,3006 2140,2998q2139 3057Q2139 3010q2140 2998);"/>
                    <Edge cubics="!1862 2959(;1862,2958 1862,2958 1862,2957q1862 2959Q1862 2958q1862 2957);"/>
                    <Edge cubics="!1862 2957(;1863,2956 1863,2956 1863,2956q1862 2957Q1863 2956q1863 2956);"/>
                    <Edge cubics="!1887 2957(;1888,2957 1889,2957 1891,2958q1887 2957Q1888 2957q1891 2958);"/>
                    <Edge cubics="!1889 2955(;1888,2956 1887,2956 1887,2957q1889 2955Q1887 2956q1887 2957);"/>
                    <Edge cubics="!1863 2956(;1866,2950 1870,2943 1876,2935q1863 2956Q1867 2947q1876 2935);"/>
                    <Edge cubics="!1867 2997(;1865,2987 1864,2978 1863,2971q1867 2997Q1864 2982q1863 2971);"/>
                    <Edge cubics="!1863 2971(;1861,2969 1860,2968 1860,2967q1863 2971Q1860 2968q1860 2967);"/>
                    <Edge cubics="!1908 3000(;1906,2999 1904,2998 1903,2997q1908 3000Q1905 2998q1903 2997);"/>
                    <Edge cubics="!1860 2967(;1860,2965 1861,2962 1862,2959q1860 2967Q1860 2964q1862 2959);"/>
                    <Edge cubics="!1928 3092(;1928,3079 1926,3062 1921,3041q1928 3092Q1928 3072q1921 3041);"/>
                    <Edge cubics="!1871 3036(;1872,3027 1870,3014 1867,2997q1871 3036Q1872 3022q1867 2997);"/>
                    <Edge cubics="!1903 2997(;1906,3005 1908,3014 1911,3024q1903 2997Q1907 3009q1911 3024);"/>
                    <Edge cubics="!1944 2142(;1944,2164 1961,2185 1961,2208q1944 2142Q1944 2153q1953 2175Q1961 2196q1961 2208);"/>
                    <Edge cubics="!1961 2208(;1961,2230 1959,2241 1958,2254q1961 2208Q1961 2215q1958 2254);"/>
                    <Edge cubics="!1958 2254(;1958,2254 1950,2254 1950,2254q1958 2254 1950 2254);"/>
                    <Edge cubics="!1950 2254(;1924,2101 1855,1918 1810,1774q1950 2254Q1934 2159q1887 2011Q1833 1846q1810 1774);"/>
                    <Edge cubics="!1810 1774(;1787,1698 1744,1597 1706,1531q1810 1774Q1770 1643q1706 1531);"/>
                    <Edge cubics="!1706 1531(;1666,1463 1539,1356 1490,1294q1706 1531Q1683 1492q1601 1410Q1507 1316q1490 1294);"/>
                    <Edge cubics="!1490 1294(;1365,1139 1195,981 1089,832q1490 1294Q1439 1231q1282 1061Q1148 915q1089 832);"/>
                    <Edge cubics="!1089 832(;973,669 874,519 681,384q1089 832Q965 658q914 598Q808 473q681 384);"/>
                    <Edge cubics="!681 384(;844,445 1008,640 1095,781q681 384Q793 426q917 553Q1018 657q1095 781);"/>
                    <Edge cubics="!1095 781(;1198,906 1373,1089 1481,1224q1095 781Q1141 837q1286 999Q1423 1151q1481 1224);"/>
                    <Edge cubics="!1481 1224(;1600,1372 1746,1527 1803,1683q1481 1224Q1541 1298q1665 1451Q1767 1584q1803 1683);"/>
                    <Edge cubics="!1803 1683(;1860,1834 1944,1996 1944,2142q1803 1683Q1832 1759q1895 1914Q1944 2050q1944 2142);"/>
                    <Edge cubics="!2121 2611(;2121,2633 2117,2631 2117,2637q2121 2611Q2121 2633q2117 2637);"/>
                    <Edge cubics="!2117 2637(;2117,2637 2108,2640 2108,2640q2117 2637 2108 2640);"/>
                    <Edge cubics="!2108 2640(;2095,2587 2093,2500 2093,2478q2108 2640Q2093 2579q2093 2478);"/>
                    <Edge cubics="!3611 463(;3611,463 3611,473 3611,496q3611 463 3611 496);"/>
                    <Edge cubics="!3611 496(;3611,887 3034,1231 2873,1616q3611 496Q3611 629q3518 782Q3451 893q3302 1058Q3070 1317q3056 1334Q2925 1492q2873 1616);"/>
                    <Edge cubics="!2419 2160(;2669,1948 2768,1795 2846,1590q2419 2160Q2598 2008q2697 1872Q2784 1753q2846 1590);"/>
                    <Edge cubics="!2846 1590(;2989,1221 3598,859 3594,459q2846 1590Q2892 1471q3024 1314Q3036 1300q3275 1036Q3429 867q3499 753Q3595 595q3594 459);"/>
                    <Edge cubics="!3594 459(;3594,459 3607,457 3607,457q3594 459 3607 457);"/>
                    <Edge cubics="!3607 457(;3607,457 3611,463 3611,463q3607 457 3611 463);"/>
                    <Edge cubics="!1063 4995(;1063,4995 1054,4989 1054,4989q1063 4995 1054 4989);"/>
                    <Edge cubics="!1994 3976(;1994,3976 2001,3976 2001,3976q1994 3976 2001 3976);"/>
                    <Edge cubics="!2202 4185(;2237,4487 2500,4815 2840,5118q2202 4185Q2249 4591q2840 5118);"/>
                    <Edge cubics="!2840 5118(;2840,5118 2836,5125 2836,5125q2840 5118 2836 5125);"/>
                    <Edge cubics="!2836 5125(;2495,4861 2192,4486 2192,4200q2836 5125Q2563 4914q2386 4671Q2192 4404q2192 4200);"/>
                    <Edge cubics="!2192 4200(;2192,4178 2193,4187 2193,4187q2192 4200Q2192 4186q2193 4185Q2193 4187q2193 4187);"/>
                    <Edge cubics="!2193 4187(;2193,4187 2202,4185 2202,4185q2193 4187 2202 4185);"/>
                    <Edge cubics="!1878 3838(;1878,3838 1871,3850 1871,3828q1878 3838Q1871 3850q1871 3828);"/>
                    <Edge cubics="!2003 3985(;2012,3998 2012,4005 2012,4027q2003 3985Q2009 3994q2011 4003Q2012 4009q2012 4027);"/>
                    <Edge cubics="!1700 5337(;1700,5337 1689,5333 1689,5333q1700 5337 1689 5333);"/>
                    <Edge cubics="!1689 5333(;1706,5292 1727,5231 1738,5188q1689 5333Q1720 5258q1738 5188);"/>
                    <Edge cubics="!1738 5188(;1738,5188 1733,5177 1733,5177q1738 5188 1733 5177);"/>
                    <Edge cubics="!1733 5177(;1733,5177 1716,5175 1716,5175q1733 5177 1716 5175);"/>
                    <Edge cubics="!1716 5175(;1716,5175 1716,5195 1716,5195q1716 5175 1716 5195);"/>
                    <Edge cubics="!1716 5195(;1713,5195 1709,5202 1700,5204q1716 5195Q1709 5202q1700 5204);"/>
                    <Edge cubics="!1607 5155(;1607,5155 1599,5168 1599,5145q1607 5155Q1599 5168q1599 5145);"/>
                    <Edge cubics="!1599 5145(;1599,5103 1793,4784 1862,4559q1599 5145Q1599 5130q1705 4921Q1823 4686q1862 4559);"/>
                    <Edge cubics="!1448 5392(;1448,5392 1437,5386 1437,5386q1448 5392 1437 5386);"/>
                    <Edge cubics="!3530 5126(;3530,5140 3498,5195 3466,5195q3530 5126Q3530 5140q3510 5166Q3487 5195q3466 5195);"/>
                    <Edge cubics="!3466 5195(;3449,5195 3407,5131 3394,5118q3466 5195Q3456 5195q3429 5161Q3401 5125q3394 5118);"/>
                    <Edge cubics="!3394 5118(;3394,5118 3389,5118 3389,5118q3394 5118 3389 5118);"/>
                    <Edge cubics="!3389 5118(;3394,5131 3405,5151 3410,5171q3389 5118Q3392 5125q3400 5142Q3407 5159q3410 5171);"/>
                    <Edge cubics="!3410 5171(;3407,5177 3403,5184 3392,5188q3410 5171Q3404 5184q3392 5188);"/>
                    <Edge cubics="!2873 1616(;2838,1699 2783,1791 2706,1894q2873 1616Q2821 1740q2706 1894);"/>
                    <Edge cubics="!2160 2660(;2183,2666 2201,2672 2216,2678q2160 2660Q2194 2669q2216 2678);"/>
                    <Edge cubics="!2223 2430(;2274,2317 2340,2227 2419,2160q2223 2430Q2300 2261q2419 2160);"/>
                    <Edge cubics="!2064 2995(;2064,2996 2064,2996 2064,2997q2064 2995Q2064 2996q2064 2997);"/>
                    <Edge cubics="!2053 2955(;2053,2955 2055,2964 2055,2964q2053 2955 2055 2964);"/>
                    <Edge cubics="!2025 2915(;1997,2914 1979,2914 1970,2913q2025 2915Q1983 2914q1970 2913);"/>
                    <Edge cubics="!1983 3107(;1983,3086 1983,3064 1983,3042q1983 3107Q1983 3075q1983 3042);"/>
                    <Edge cubics="!2050 3050(;2051,3065 2051,3081 2051,3098q2050 3050Q2051 3073q2051 3098);"/>
                    <Edge cubics="!2064 2997(;2064,3000 2059,3018 2050,3050q2064 2997Q2064 3002q2050 3050);"/>
                    <Edge cubics="!1983 3042(;1983,3042 1984,3007 1984,3007q1983 3042 1984 3007);"/>
                    <Edge cubics="!1980 3237(;1976,3236 1974,3232 1974,3223q1980 3237Q1974 3236q1974 3223);"/>
                    <Edge cubics="!2036 3220(;2031,3264 2023,3320 2012,3388q2036 3220Q2028 3286q2012 3388);"/>
                    <Edge cubics="!2051 3098(;2051,3136 2046,3177 2036,3220q2051 3098Q2051 3155q2036 3220);"/>
                    <Edge cubics="!1974 3223(;1974,3208 1976,3180 1980,3141q1974 3223Q1974 3200q1980 3141);"/>
                    <Edge cubics="!1939 3651(;1946,3615 1952,3578 1957,3541q1939 3651Q1949 3597q1957 3541);"/>
                    <Edge cubics="!1907 3790(;1898,3809 1888,3825 1878,3838q1907 3790Q1893 3818q1878 3838);"/>
                    <Edge cubics="!2282 3885(;2238,3807 2205,3747 2182,3706q2282 3885Q2216 3768q2182 3706);"/>
                    <Edge cubics="!1957 3541(;1968,3456 1976,3354 1980,3237q1957 3541Q1974 3413q1980 3237);"/>
                    <Edge cubics="!2182 3706(;2135,3621 2106,3549 2095,3492q2182 3706Q2111 3578q2095 3492);"/>
                    <Edge cubics="!2127 3416(;2144,3601 2210,3754 2323,3873q2127 3416Q2153 3694q2323 3873);"/>
                    <Edge cubics="!2002 3989(;2002,3988 2002,3986 2003,3985q2002 3989Q2002 3987q2003 3985);"/>
                    <Edge cubics="!2001 3976(;2001,3980 2001,3984 2002,3989q2001 3976Q2001 3982q2002 3989);"/>
                    <Edge cubics="!2007 4068(;2007,4069 2007,4070 2007,4071q2007 4068Q2007 4069q2007 4071);"/>
                    <Edge cubics="!2012 4027(;2012,4031 2010,4045 2007,4068q2012 4027Q2012 4033q2007 4068);"/>
                    <Edge cubics="!1986 4041(;1989,4018 1991,3996 1994,3976q1986 4041Q1990 4006q1994 3976);"/>
                    <Edge cubics="!1958 4489(;1958,4511 1949,4559 1932,4634q1958 4489Q1958 4522q1932 4634);"/>
                    <Edge cubics="!1862 4559(;1881,4497 1905,4398 1933,4263q1862 4559Q1891 4466q1933 4263);"/>
                    <Edge cubics="!2282 3888(;2282,3887 2282,3886 2282,3885q2282 3888Q2282 3886q2282 3885);"/>
                    <Edge cubics="!3109 4642(;3110,4644 3110,4646 3111,4648q3109 4642Q3110 4645q3111 4648);"/>
                    <Edge cubics="!3115 4647(;3112,4645 3110,4643 3109,4642q3115 4647Q3111 4644q3109 4642);"/>
                    <Edge cubics="!3111 4648(;3112,4647 3113,4647 3115,4647q3111 4648Q3112 4647q3115 4647);"/>
                    <Edge cubics="!3127 4827(;3091,4770 3061,4722 3037,4682q3127 4827Q3073 4742q3037 4682);"/>
                    <Edge cubics="!3236 4750(;3245,4761 3255,4772 3266,4785q3236 4750Q3250 4766q3266 4785);"/>
                    <Edge cubics="!3266 4785(;3281,4799 3295,4814 3309,4831q3266 4785Q3288 4806q3309 4831);"/>
                    <Edge cubics="!3239 4743(;3239,4746 3238,4748 3236,4750q3239 4743Q3239 4747q3236 4750);"/>
                    <Edge cubics="!3037 4682(;3008,4650 2974,4610 2934,4561q3037 4682Q2994 4634q2934 4561);"/>
                    <Edge cubics="!2934 4561(;2812,4414 2734,4333 2700,4320q2934 4561Q2751 4340q2700 4320);"/>
                    <Edge cubics="!1951 2881(;1954,2888 1957,2895 1962,2901q1951 2881Q1955 2892q1962 2901);"/>
                    <Edge cubics="!2706 1894(;2672,1939 2598,2029 2485,2165q2706 1894Q2655 1961q2485 2165);"/>
                    <Edge cubics="!3488 5060(;3487,5061 3487,5061 3486,5062q3488 5060Q3487 5061q3486 5062);"/>
                    <Edge cubics="!3493 5050(;3492,5055 3490,5058 3488,5060q3493 5050Q3491 5057q3488 5060);"/>
                    <Edge cubics="!3486 5062(;3515,5101 3530,5122 3530,5126q3486 5062Q3530 5120q3530 5126);"/>
                    <Edge cubics="!1700 5204(;1693,5199 1686,5196 1678,5195q1700 5204Q1690 5197q1678 5195);"/>
                    <Edge cubics="!1678 5195(;1674,5194 1665,5187 1651,5174q1678 5195Q1672 5194q1651 5174);"/>
                    <Edge cubics="!1612 5155(;1611,5155 1609,5155 1607,5155q1612 5155Q1610 5155q1607 5155);"/>
                    <Edge cubics="!1860 4973(;1817,5102 1764,5224 1700,5337q1860 4973Q1796 5167q1700 5337);"/>
                    <Edge cubics="!3392 5188(;3329,5127 3240,5006 3127,4827q3392 5188Q3297 5096q3127 4827);"/>
                    <Edge cubics="!3309 4831(;3352,4880 3413,4953 3493,5050q3309 4831Q3373 4905q3493 5050);"/>
                    <Edge cubics="!1932 4634(;1926,4732 1902,4845 1860,4973q1932 4634Q1923 4781q1860 4973);"/>
                    <Edge cubics="!1841 4073(;1689,4412 1430,4719 1063,4995q1841 4073Q1613 4581q1063 4995);"/>
                    <Edge cubics="!1054 4989(;1448,4628 1709,4297 1836,3995q1054 4989Q1645 4448q1836 3995);"/>
                    <Edge cubics="!2522 1123(;2675,750 2625,695 2625,380q2522 1123Q2621 882q2631 730Q2625 538q2625 380);"/>
                    <Edge cubics="!2625 380(;2625,366 2633,310 2643,308q2625 380Q2625 365q2630 340Q2636 309q2643 308);"/>
                    <Edge cubics="!2338 1658(;2338,1658 2338,1665 2331,1669q2338 1658Q2338 1665q2331 1669);"/>
                    <Edge cubics="!4896 423(;4896,423 4904,435 4904,435q4896 423 4904 435);"/>
                    <Edge cubics="!4904 435(;3987,779 3612,1152 3274,1542q4904 435Q4283 668q3872 971Q3585 1183q3274 1542);"/>
                    <Edge cubics="!1940 2496(;1940,2464 1931,2388 1968,2374q1940 2496Q1940 2430q1940 2428Q1945 2383q1968 2374);"/>
                    <Edge cubics="!1639 240(;1639,240 1652,238 1652,238q1639 240 1652 238);"/>
                    <Edge cubics="!1983 1141(;1983,1164 1981,1198 1976,1224q1983 1141Q1983 1188q1976 1224);"/>
                    <Edge cubics="!1976 1224(;1976,1224 1968,1224 1968,1224q1976 1224 1968 1224);"/>
                    <Edge cubics="!2001 1127(;2003,1206 2003,1292 2001,1377q2001 1127Q2004 1247q2001 1377);"/>
                    <Edge cubics="!2001 1377(;2001,1377 1994,1377 1994,1377q2001 1377 1994 1377);"/>
                    <Edge cubics="!1994 1377(;1994,1377 1992,1354 1992,1332q1994 1377Q1992 1354q1992 1332);"/>
                    <Edge cubics="!1992 1332(;1992,1309 1994,1127 1994,1127q1992 1332 1994 1127);"/>
                    <Edge cubics="!1994 1127(;1994,1127 2001,1127 2001,1127q1994 1127 2001 1127);"/>
                    <Edge cubics="!4453 401(;4451,399 4449,397 4448,396q4453 401Q4450 398q4448 396);"/>
                    <Edge cubics="!4470 387(;4471,388 4473,388 4474,389q4470 387Q4472 388q4474 389);"/>
                    <Edge cubics="!4468 389(;4469,388 4469,388 4470,387q4468 389Q4469 388q4470 387);"/>
                    <Edge cubics="!4448 396(;4455,392 4461,390 4468,389q4448 396Q4458 390q4468 389);"/>
                    <Edge cubics="!4474 389(;4486,388 4498,393 4510,402q4474 389Q4492 388q4510 402);"/>
                    <Edge cubics="!4868 433(;4877,430 4887,426 4896,423q4868 433Q4882 428q4896 423);"/>
                    <Edge cubics="!4678 410(;4763,415 4826,422 4868,433q4678 410Q4805 417q4868 433);"/>
                    <Edge cubics="!1913 866(;1896,795 1871,719 1838,638q1913 866Q1887 759q1838 638);"/>
                    <Edge cubics="!1652 238(;1759,411 1832,541 1870,626q1652 238Q1813 498q1870 626);"/>
                    <Edge cubics="!1838 638(;1793,528 1726,395 1639,240q1838 638Q1770 473q1639 240);"/>
                    <Edge cubics="!2688 296(;2688,296 2689,293 2689,293q2688 296 2689 293);"/>
                    <Edge cubics="!2689 293(;2692,290 2695,287 2700,284q2689 293Q2693 288q2700 284);"/>
                    <Edge cubics="!2727 287(;2731,281 2738,275 2748,268q2727 287Q2733 278q2748 268);"/>
                    <Edge cubics="!2723 295(;2724,292 2726,290 2727,287q2723 295Q2725 291q2727 287);"/>
                    <Edge cubics="!2712 294(;2715,294 2719,294 2723,295q2712 294Q2717 294q2723 295);"/>
                    <Edge cubics="!2700 284(;2705,287 2709,290 2712,294q2700 284Q2708 288q2712 294);"/>
                    <Edge cubics="!2643 308(;2644,316 2646,328 2647,343q2643 308Q2645 320q2647 343);"/>
                    <Edge cubics="!2647 343(;2652,316 2666,301 2688,296q2647 343Q2655 303q2688 296);"/>
                    <Edge cubics="!2762 323(;2765,344 2767,360 2768,371q2762 323Q2767 354q2768 371);"/>
                    <Edge cubics="!2748 268(;2753,277 2757,295 2762,323q2748 268Q2755 281q2762 323);"/>
                    <Edge cubics="!2768 371(;2774,404 2777,443 2777,486q2768 371Q2777 421q2777 486);"/>
                    <Edge cubics="!3274 1542(;3057,1797 2893,1988 2780,2115q3274 1542Q2949 1925q2780 2115);"/>
                    <Edge cubics="!2436 1316(;2477,1227 2505,1163 2522,1123q2436 1316Q2497 1183q2522 1123);"/>
                    <Edge cubics="!1959 1001(;1966,1042 1974,1089 1983,1141q1959 1001Q1970 1063q1983 1141);"/>
                    <Edge cubics="!1968 1224(;1955,1147 1944,1082 1935,1029q1968 1224Q1948 1109q1935 1029);"/>
                    <Edge cubics="!2449 1445(;2414,1502 2383,1556 2356,1609q2449 1445Q2397 1530q2356 1609);"/>
                    <Edge cubics="!2306 1579(;2312,1568 2318,1558 2324,1549q2306 1579Q2315 1563q2324 1549);"/>
                    <Edge cubics="!2331 1669(;2329,1668 2328,1667 2327,1666q2331 1669Q2328 1667q2327 1666);"/>
                    <Edge cubics="!2356 1609(;2348,1628 2342,1644 2338,1658q2356 1609Q2344 1637q2338 1658);"/>
                    <Edge cubics="!2324 1549(;2339,1516 2351,1487 2362,1462q2324 1549Q2346 1499q2362 1462);"/>
                    <Edge cubics="!2196 1808(;2207,1761 2243,1684 2306,1579q2196 1808Q2212 1737q2306 1579);"/>
                    <Edge cubics="!2362 1462(;2390,1399 2415,1351 2436,1316q2362 1462Q2404 1368q2436 1316);"/>
                    <Edge cubics="!2159 1923(;2160,1918 2162,1913 2163,1908q2159 1923Q2161 1916q2163 1908);"/>
                    <Edge cubics="!2121 2154(;2120,2142 2120,2128 2120,2113q2121 2154Q2120 2136q2120 2113);"/>
                    <Edge cubics="!2122 2068(;2125,2024 2132,1987 2143,1957q2122 2068Q2126 2002q2143 1957);"/>
                    <Edge cubics="!2121 2075(;2121,2073 2121,2071 2122,2068q2121 2075Q2121 2072q2122 2068);"/>
                    <Edge cubics="!2120 2113(;2120,2100 2120,2087 2121,2075q2120 2113Q2120 2093q2121 2075);"/>
                    <Edge cubics="!2004 2481(;2006,2489 2007,2501 2008,2516q2004 2481Q2007 2493q2008 2516);"/>
                    <Edge cubics="!2007 2610(;2006,2607 2005,2604 2004,2601q2007 2610Q2005 2605q2004 2601);"/>
                    <Edge cubics="!2002 2607(;2003,2608 2005,2609 2007,2610q2002 2607Q2004 2608q2007 2610);"/>
                    <Edge cubics="!2004 2601(;2003,2602 2003,2604 2002,2607q2004 2601Q2003 2603q2002 2607);"/>
                    <Edge cubics="!2008 2516(;2013,2527 2020,2540 2028,2555q2008 2516Q2016 2532q2028 2555);"/>
                    <Edge cubics="!2028 2555(;2046,2590 2057,2616 2061,2631q2028 2555Q2055 2608q2061 2631);"/>
                    <Edge cubics="!1874 2807(;1877,2806 1881,2806 1885,2806q1874 2807Q1879 2806q1885 2806);"/>
                    <Edge cubics="!1885 2806(;1885,2805 1885,2805 1885,2804q1885 2806Q1885 2805q1885 2804);"/>
                    <Edge cubics="!1936 2827(;1935,2832 1934,2837 1933,2842q1936 2827Q1934 2835q1933 2842);"/>
                    <Edge cubics="!2011 2708(;2009,2707 2007,2705 2006,2704q2011 2708Q2008 2706q2006 2704);"/>
                    <Edge cubics="!2034 2696(;2033,2695 2033,2695 2033,2694q2034 2696Q2033 2695q2033 2694);"/>
                    <Edge cubics="!2033 2694(;2030,2693 2026,2692 2023,2691q2033 2694Q2028 2692q2023 2691);"/>
                    <Edge cubics="!2022 2692(;2022,2692 2022,2692 2023,2693q2022 2692Q2022 2692q2023 2693);"/>
                    <Edge cubics="!2023 2691(;2022,2691 2022,2691 2022,2692q2023 2691Q2022 2691q2022 2692);"/>
                    <Edge cubics="!2003 2723(;2016,2734 2023,2741 2024,2744q2003 2723Q2023 2740q2024 2744);"/>
                    <Edge cubics="!2006 2704(;2002,2707 1997,2710 1992,2714q2006 2704Q2000 2708q1992 2714);"/>
                    <Edge cubics="!1992 2714(;1995,2717 1998,2720 2003,2723q1992 2714Q1996 2718q2003 2723);"/>
                    <Edge cubics="!2047 2727(;2033,2723 2021,2717 2011,2708q2047 2727Q2026 2721q2011 2708);"/>
                    <Edge cubics="!2023 2693(;2042,2708 2052,2718 2054,2721q2023 2693Q2051 2716q2054 2721);"/>
                    <Edge cubics="!2188 2768(;2187,2766 2187,2764 2188,2763q2188 2768Q2187 2765q2188 2763);"/>
                    <Edge cubics="!2188 2763(;2184,2762 2182,2761 2181,2760q2188 2763Q2182 2761q2181 2760);"/>
                    <Edge cubics="!2182 2772(;2184,2770 2186,2769 2188,2768q2182 2772Q2185 2769q2188 2768);"/>
                    <Edge cubics="!2226 2796(;2226,2796 2226,2796 2226,2797q2226 2796Q2226 2796q2226 2797);"/>
                    <Edge cubics="!2189 2786(;2189,2784 2189,2782 2189,2781q2189 2786Q2189 2783q2189 2781);"/>
                    <Edge cubics="!2189 2781(;2186,2781 2183,2782 2179,2783q2189 2781Q2185 2781q2179 2783);"/>
                    <Edge cubics="!2154 2795(;2167,2792 2179,2789 2189,2786q2154 2795Q2174 2791q2189 2786);"/>
                    <Edge cubics="!2248 2750(;2247,2767 2239,2783 2226,2796q2248 2750Q2246 2776q2226 2796);"/>
                    <Edge cubics="!2252 2703(;2252,2722 2251,2737 2248,2750q2252 2703Q2252 2731q2248 2750);"/>
                    <Edge cubics="!2168 2778(;2174,2777 2179,2775 2182,2772q2168 2778Q2177 2776q2182 2772);"/>
                    <Edge cubics="!2381 2535(;2338,2598 2295,2653 2252,2702q2381 2535Q2317 2629q2252 2702);"/>
                    <Edge cubics="!2143 1957(;2146,1948 2152,1937 2159,1923q2143 1957Q2148 1944q2159 1923);"/>
                    <Edge cubics="!2327 1666(;2283,1753 2249,1834 2224,1909q2327 1666Q2261 1796q2224 1909);"/>
                    <Edge cubics="!2163 1908(;2175,1869 2186,1835 2196,1808q2163 1908Q2181 1849q2196 1808);"/>
                    <Edge cubics="!2780 2115(;2639,2274 2506,2414 2381,2535q2780 2115Q2569 2353q2381 2535);"/>
                    <Edge cubics="!2675 1034(;2641,1115 2566,1252 2449,1445q2675 1034Q2624 1156q2449 1445);"/>
                    <Edge cubics="!1870 626(;1929,757 1958,882 1959,1001q1870 626Q1958 823q1959 1001);"/>
                    <Edge cubics="!1935 1029(;1924,960 1916,905 1913,866q1935 1029Q1918 925q1913 866);"/>
                    <Edge cubics="!2777 486(;2777,685 2743,867 2675,1034q2777 486Q2777 784q2675 1034);"/>
                    <Edge cubics="!519 4828(;519,4720 1214,4185 1229,4176q519 4828Q519 4760q868 4465Q1165 4215q1229 4176);"/>
                    <Edge cubics="!3664 0(;3942,23 4012,47 4376,102q3664 0Q3832 14q3988 39Q4086 55q4376 102);"/>
                    <Edge cubics="!4376 102(;4784,163 5119,150 5119,265q4376 102Q4580 133q4901 163Q5119 194q5119 265);"/>
                    <Edge cubics="!5119 265(;5119,433 4347,640 4052,856q5119 265Q5119 359q4696 543Q4360 688q4343 696Q4147 787q4052 856);"/>
                    <Edge cubics="!4052 856(;3718,1101 3578,1248 3324,1516q4052 856Q3823 1024q3658 1177Q3548 1280q3324 1516);"/>
                    <Edge cubics="!3324 1516(;3131,1721 2987,1949 2739,2180q3324 1516Q3260 1585q3052 1838Q2881 2048q2739 2180);"/>
                    <Edge cubics="!2739 2180(;2538,2367 2396,2815 2294,2826q2739 2180Q2637 2275q2479 2569Q2344 2821q2294 2826);"/>
                    <Edge cubics="!2294 2826(;2296,2840 2296,2850 2296,2873q2294 2826Q2296 2840q2296 2873);"/>
                    <Edge cubics="!2296 2873(;2296,2982 2219,2954 2219,3027q2296 2873Q2296 2932q2258 2964Q2219 2995q2219 3027);"/>
                    <Edge cubics="!2219 3027(;2219,3327 2540,3822 2708,4056q2219 3027Q2219 3225q2401 3566Q2526 3803q2708 4056);"/>
                    <Edge cubics="!2708 4056(;2837,4237 3052,4360 3403,4534q2708 4056Q2798 4183q2972 4298Q3111 4389q3403 4534);"/>
                    <Edge cubics="!3403 4534(;3880,4772 4076,4779 4076,4992q3403 4534Q3642 4653q3918 4772Q4003 4818q4038 4864Q4076 4915q4076 4992);"/>
                    <Edge cubics="!4076 4992(;4076,5171 3735,5419 3243,5419q4076 4992Q4076 5139q3844 5273Q3589 5419q3243 5419);"/>
                    <Edge cubics="!3243 5419(;3171,5419 3015,5476 2923,5485q3243 5419Q3205 5419q3091 5449Q2966 5481q2923 5485);"/>
                    <Edge cubics="!2923 5485(;2923,5485 1355,5485 1355,5485q2923 5485 1355 5485);"/>
                    <Edge cubics="!1355 5485(;1253,5470 771,5403 633,5290q1355 5485Q765 5398q633 5290);"/>
                    <Edge cubics="!633 5290(;460,5148 456,5124 456,5004q633 5290Q508 5187q480 5139Q456 5098q456 5004);"/>
                    <Edge cubics="!1571 3847(;1571,3773 1832,3462 1832,2976q1571 3847Q1571 3827q1612 3748Q1674 3628q1702 3566Q1832 3271q1832 2976);"/>
                    <Edge cubics="!1832 2976(;1832,2972 1806,2824 1806,2799q1832 2976Q1806 2824q1806 2799);"/>
                    <Edge cubics="!1806 2799(;1806,2772 1834,2644 1834,2641q1806 2799Q1806 2783q1820 2711Q1834 2643q1834 2641);"/>
                    <Edge cubics="!1834 2641(;1834,2594 1670,2178 1639,1987q1834 2641Q1834 2624q1748 2368Q1657 2095q1639 1987);"/>
                    <Edge cubics="!1639 1987(;1607,1778 1251,1568 1049,1356q1639 1987Q1620 1861q1408 1673Q1150 1462q1049 1356);"/>
                    <Edge cubics="!1049 1356(;968,1272 655,1184 554,1108q1049 1356Q1005 1311q809 1229Q598 1141q554 1108);"/>
                    <Edge cubics="!554 1108(;414,1003 390,893 329,786q554 1108Q466 1042q412 948Q360 840q329 786);"/>
                    <Edge cubics="!329 786(;290,722 0,290 0,142q329 786Q227 630q150 496Q0 235q0 142);"/>
                    <Edge cubics="!0 142(;0,76 -19,32 179,2q0 142Q0 76q15 59Q47 22q179 2);"/>
                    <Edge cubics="!179 2(;179,2 3686,2 3686,2q179 2 3686 2);"/>
                    <Edge cubics="!4627 408(;4642,409 4659,409 4678,410q4627 408Q4650 409q4678 410);"/>
                    <Edge cubics="!4510 402(;4523,403 4562,405 4627,408q4510 402Q4529 404q4627 408);"/>
                    <Edge cubics="!3583 1(;3583,1 3664,0 3664,0q3583 1 3664 0);"/>
                    <Edge cubics="!3686 2(;3686,2 3583,1 3583,1q3686 2 3583 1);"/>
                    <Edge cubics="!3647 1040(;3676,1015 3706,989 3737,964q3647 1040Q3691 1002q3737 964);"/>
                    <Edge cubics="!2984 1701(;3022,1656 3062,1609 3105,1559q2984 1701Q3041 1634q3105 1559);"/>
                    <Edge cubics="!2606 2146(;2669,2069 2795,1920 2984,1701q2606 2146Q2701 2030q2984 1701);"/>
                    <Edge cubics="!3105 1559(;3232,1411 3413,1238 3647,1040q3105 1559Q3296 1337q3647 1040);"/>
                    <Edge cubics="!1968 2374(;1970,2379 1972,2383 1973,2388q1968 2374Q1971 2381q1973 2388);"/>
                    <Edge cubics="!2093 2478(;2093,2473 2093,2467 2093,2461q2093 2478Q2093 2470q2093 2461);"/>
                    <Edge cubics="!1983 2416(;1995,2453 2002,2474 2004,2481q1983 2416Q2001 2471q2004 2481);"/>
                    <Edge cubics="!1960 2592(;1957,2579 1954,2568 1952,2558q1960 2592Q1955 2573q1952 2558);"/>
                    <Edge cubics="!1950 2591(;1953,2591 1957,2591 1960,2592q1950 2591Q1955 2591q1960 2592);"/>
                    <Edge cubics="!2061 2631(;2064,2632 2068,2633 2072,2634q2061 2631Q2066 2632q2072 2634);"/>
                    <Edge cubics="!2123 2500(;2122,2537 2121,2574 2121,2611q2123 2500Q2121 2555q2121 2611);"/>
                    <Edge cubics="!1942 2513(;1941,2506 1940,2500 1940,2496q1942 2513Q1940 2502q1940 2496);"/>
                    <Edge cubics="!1942 2830(;1939,2829 1937,2828 1936,2827q1942 2830Q1938 2828q1936 2827);"/>
                    <Edge cubics="!1944 2860(;1943,2859 1941,2859 1940,2858q1944 2860Q1942 2859q1940 2858);"/>
                    <Edge cubics="!1933 2842(;1936,2843 1938,2844 1941,2846q1933 2842Q1937 2843q1941 2846);"/>
                    <Edge cubics="!2069 2728(;2068,2728 2067,2728 2066,2728q2069 2728Q2067 2728q2066 2728);"/>
                    <Edge cubics="!2066 2728(;2064,2727 2062,2726 2061,2725q2066 2728Q2063 2726q2061 2725);"/>
                    <Edge cubics="!1947 2849(;1948,2849 1948,2849 1949,2850q1947 2849Q1948 2849q1949 2850);"/>
                    <Edge cubics="!1949 2850(;1950,2851 1952,2852 1954,2853q1949 2850Q1951 2851q1954 2853);"/>
                    <Edge cubics="!1956 2867(;1953,2866 1951,2864 1948,2862q1956 2867Q1952 2865q1948 2862);"/>
                    <Edge cubics="!1947 2872(;1948,2875 1950,2878 1951,2881q1947 2872Q1949 2876q1951 2881);"/>
                    <Edge cubics="!1954 2853(;1961,2858 1970,2864 1982,2871q1954 2853Q1964 2860q1982 2871);"/>
                    <Edge cubics="!1972 2874(;1970,2874 1965,2872 1956,2867q1972 2874Q1969 2874q1956 2867);"/>
                    <Edge cubics="!2129 2819(;2129,2819 2130,2818 2130,2818q2129 2819 2130 2818);"/>
                    <Edge cubics="!2107 2825(;2113,2824 2120,2822 2129,2819q2107 2825Q2116 2823q2129 2819);"/>
                    <Edge cubics="!2061 2784(;2070,2789 2079,2794 2088,2799q2061 2784Q2074 2791q2088 2799);"/>
                    <Edge cubics="!2089 2830(;2078,2830 2067,2830 2057,2829q2089 2830Q2072 2830q2057 2829);"/>
                    <Edge cubics="!2091 2878(;2075,2878 2062,2877 2052,2876q2091 2878Q2067 2878q2052 2876);"/>
                    <Edge cubics="!2049 2895(;2049,2895 2050,2895 2050,2895q2049 2895 2050 2895);"/>
                    <Edge cubics="!2134 2869(;2127,2871 2120,2873 2115,2874q2134 2869Q2123 2872q2115 2874);"/>
                    <Edge cubics="!2115 2874(;2104,2877 2096,2878 2091,2878q2115 2874Q2098 2878q2091 2878);"/>
                    <Edge cubics="!2055 2849(;2083,2847 2107,2843 2126,2837q2055 2849Q2097 2846q2126 2837);"/>
                    <Edge cubics="!2030 2850(;2039,2850 2047,2850 2055,2849q2030 2850Q2043 2850q2055 2849);"/>
                    <Edge cubics="!2057 2829(;2036,2827 2016,2823 1999,2818q2057 2829Q2025 2826q1999 2818);"/>
                    <Edge cubics="!1986 2745(;2007,2755 2032,2768 2061,2784q1986 2745Q2017 2760q2061 2784);"/>
                    <Edge cubics="!2052 2876(;2032,2873 2022,2867 2022,2859q2052 2876Q2022 2871q2022 2859);"/>
                    <Edge cubics="!1952 2558(;1947,2539 1944,2524 1942,2513q1952 2558Q1945 2529q1942 2513);"/>
                    <Edge cubics="!1926 2594(;1933,2591 1941,2590 1950,2591q1926 2594Q1937 2590q1950 2591);"/>
                    <Edge cubics="!1941 2846(;1943,2847 1945,2848 1947,2849q1941 2846Q1944 2847q1947 2849);"/>
                    <Edge cubics="!2072 2634(;2090,2640 2112,2646 2137,2653q2072 2634Q2099 2643q2137 2653);"/>
                    <Edge cubics="!1940 2858(;1943,2862 1945,2867 1947,2872q1940 2858Q1944 2864q1947 2872);"/>
                    <Edge cubics="!1948 2862(;1947,2861 1945,2861 1944,2860q1948 2862Q1946 2861q1944 2860);"/>
                    <Edge cubics="!1950 2834(;1947,2833 1944,2831 1942,2830q1950 2834Q1945 2832q1942 2830);"/>
                    <Edge cubics="!2167 2569(;2188,2512 2207,2466 2223,2430q2167 2569Q2199 2484q2223 2430);"/>
                    <Edge cubics="!2325 2524(;2332,2514 2339,2504 2346,2494q2325 2524Q2335 2509q2346 2494);"/>
                    <Edge cubics="!2217 2679(;2218,2677 2219,2675 2220,2674q2217 2679Q2219 2676q2220 2674);"/>
                    <Edge cubics="!2163 2748(;2158,2748 2153,2748 2148,2747q2163 2748Q2155 2748q2148 2747);"/>
                    <Edge cubics="!2226 2797(;2226,2806 2222,2816 2214,2828q2226 2797Q2226 2810q2214 2828);"/>
                    <Edge cubics="!2190 2847(;2190,2847 2191,2848 2191,2848q2190 2847 2191 2848);"/>
                    <Edge cubics="!2191 2847(;2191,2847 2190,2847 2190,2847q2191 2847 2190 2847);"/>
                    <Edge cubics="!2189 2891(;2186,2886 2183,2883 2178,2880q2189 2891Q2185 2884q2178 2880);"/>
                    <Edge cubics="!2191 2848(;2197,2863 2203,2876 2209,2889q2191 2848Q2200 2870q2209 2889);"/>
                    <Edge cubics="!2214 2828(;2206,2839 2198,2846 2191,2847q2214 2828Q2202 2845q2191 2847);"/>
                    <Edge cubics="!2220 2674(;2245,2637 2280,2587 2325,2524q2220 2674Q2257 2619q2325 2524);"/>
                    <Edge cubics="!2185 2601(;2175,2621 2167,2641 2160,2660q2185 2601Q2170 2631q2160 2660);"/>
                    <Edge cubics="!2148 2747(;2125,2745 2106,2737 2089,2724q2148 2747Q2114 2744q2089 2724);"/>
                    <Edge cubics="!2126 2837(;2143,2831 2157,2824 2167,2815q2126 2837Q2152 2828q2167 2815);"/>
                    <Edge cubics="!2485 2165(;2342,2335 2242,2480 2185,2601q2485 2165Q2271 2420q2185 2601);"/>
                    <Edge cubics="!2137 2653(;2147,2623 2157,2595 2167,2569q2137 2653Q2152 2608q2167 2569);"/>
                    <Edge cubics="!2224 1909(;2165,2084 2132,2281 2123,2500q2224 1909Q2136 2171q2123 2500);"/>
                    <Edge cubics="!2093 2461(;2094,2353 2103,2251 2121,2154q2093 2461Q2094 2299q2121 2154);"/>
                    <Edge cubics="!2178 2880(;2167,2873 2153,2869 2134,2869q2178 2880Q2162 2869q2134 2869);"/>
                    <Edge cubics="!1973 2388(;1976,2398 1980,2407 1983,2416q1973 2388Q1978 2403q1983 2416);"/>
                    <Edge cubics="!2102 2905(;2108,2906 2115,2907 2123,2909q2102 2905Q2111 2906q2123 2909);"/>
                    <Edge cubics="!2127 2958(;2132,2958 2136,2958 2140,2958q2127 2958Q2134 2958q2140 2958);"/>
                    <Edge cubics="!2079 2993(;2074,2994 2069,2994 2064,2995q2079 2993Q2071 2994q2064 2995);"/>
                    <Edge cubics="!2082 2992(;2081,2992 2080,2992 2079,2993q2082 2992Q2080 2992q2079 2993);"/>
                    <Edge cubics="!2104 2988(;2105,2993 2105,2999 2106,3005q2104 2988Q2105 2996q2106 3005);"/>
                    <Edge cubics="!2123 2985(;2116,2986 2110,2987 2104,2988q2123 2985Q2113 2986q2104 2988);"/>
                    <Edge cubics="!2142 2981(;2135,2982 2129,2984 2123,2985q2142 2981Q2132 2983q2123 2985);"/>
                    <Edge cubics="!2055 2964(;2064,2962 2073,2961 2084,2960q2055 2964Q2068 2961q2084 2960);"/>
                    <Edge cubics="!2084 2960(;2097,2959 2111,2958 2127,2958q2084 2960Q2103 2958q2127 2958);"/>
                    <Edge cubics="!1970 2913(;1987,2932 2011,2946 2042,2953q1970 2913Q1995 2942q2042 2953);"/>
                    <Edge cubics="!1984 3007(;1979,3007 1975,3007 1971,3008q1984 3007Q1977 3007q1971 3008);"/>
                    <Edge cubics="!1971 3008(;1966,3009 1962,3009 1959,3009q1971 3008Q1964 3009q1959 3009);"/>
                    <Edge cubics="!1962 2901(;1962,2901 1963,2901 1964,2901q1962 2901Q1962 2901q1964 2901);"/>
                    <Edge cubics="!1963 3081(;1963,3086 1963,3091 1963,3097q1963 3081Q1963 3088q1963 3097);"/>
                    <Edge cubics="!1980 3141(;1980,3138 1980,3136 1981,3133q1980 3141Q1980 3137q1981 3133);"/>
                    <Edge cubics="!1981 3133(;1982,3124 1982,3115 1983,3107q1981 3133Q1982 3119q1983 3107);"/>
                    <Edge cubics="!1963 3097(;1963,3107 1963,3117 1962,3128q1963 3097Q1963 3112q1962 3128);"/>
                    <Edge cubics="!2079 3063(;2079,3062 2079,3062 2079,3061q2079 3063Q2079 3062q2079 3061);"/>
                    <Edge cubics="!2079 3118(;2079,3088 2079,3070 2079,3063q2079 3118Q2079 3073q2079 3063);"/>
                    <Edge cubics="!2079 3061(;2080,3048 2080,3036 2081,3025q2079 3061Q2080 3042q2081 3025);"/>
                    <Edge cubics="!1959 3011(;1962,3021 1963,3044 1963,3081q1959 3011Q1963 3026q1963 3081);"/>
                    <Edge cubics="!2081 3025(;2081,3013 2081,3002 2082,2992q2081 3025Q2081 3007q2082 2992);"/>
                    <Edge cubics="!2042 2953(;2045,2954 2049,2954 2053,2955q2042 2953Q2047 2954q2053 2955);"/>
                    <Edge cubics="!1921 3041(;1920,3039 1920,3037 1920,3035q1921 3041Q1920 3038q1920 3035);"/>
                    <Edge cubics="!1920 3035(;1916,3022 1912,3010 1908,3000q1920 3035Q1914 3015q1908 3000);"/>
                    <Edge cubics="!2123 3196(;2124,3219 2124,3244 2125,3270q2123 3196Q2124 3231q2125 3270);"/>
                    <Edge cubics="!2077 3232(;2078,3184 2078,3146 2079,3118q2077 3232Q2078 3160q2079 3118);"/>
                    <Edge cubics="!2106 3005(;2113,3057 2119,3121 2123,3196q2106 3005Q2117 3083q2123 3196);"/>
                    <Edge cubics="!1962 3128(;1959,3174 1951,3227 1936,3286q1962 3128Q1958 3197q1936 3286);"/>
                    <Edge cubics="!1824 3512(;1837,3478 1848,3446 1859,3415q1824 3512Q1843 3461q1859 3415);"/>
                    <Edge cubics="!1859 3523(;1852,3542 1844,3561 1837,3580q1859 3523Q1848 3552q1837 3580);"/>
                    <Edge cubics="!1872 3824(;1875,3809 1891,3768 1919,3701q1872 3824Q1877 3801q1919 3701);"/>
                    <Edge cubics="!1871 3828(;1871,3827 1871,3825 1872,3824q1871 3828Q1871 3826q1872 3824);"/>
                    <Edge cubics="!1919 3701(;1925,3686 1931,3672 1936,3659q1919 3701Q1928 3679q1936 3659);"/>
                    <Edge cubics="!1936 3659(;1937,3656 1938,3654 1939,3651q1936 3659Q1938 3655q1939 3651);"/>
                    <Edge cubics="!1837 3580(;1826,3606 1815,3632 1804,3657q1837 3580Q1820 3619q1804 3657);"/>
                    <Edge cubics="!2258 3434(;2261,3444 2265,3454 2268,3464q2258 3434Q2263 3449q2268 3464);"/>
                    <Edge cubics="!2095 3492(;2084,3433 2078,3346 2077,3232q2095 3492Q2079 3403q2077 3232);"/>
                    <Edge cubics="!1936 3286(;1919,3355 1893,3434 1859,3523q1936 3286Q1910 3390q1859 3523);"/>
                    <Edge cubics="!2125 3270(;2126,3315 2127,3364 2127,3416q2125 3270Q2127 3338q2127 3416);"/>
                    <Edge cubics="!1859 3415(;1905,3278 1928,3171 1928,3092q1859 3415Q1928 3210q1928 3092);"/>
                    <Edge cubics="!2160 2978(;2187,3160 2219,3312 2258,3434q2160 2978Q2200 3251q2258 3434);"/>
                    <Edge cubics="!2280 3579(;2236,3473 2203,3379 2180,3296q2280 3579Q2214 3420q2180 3296);"/>
                    <Edge cubics="!2180 3296(;2153,3201 2139,3121 2139,3057q2180 3296Q2139 3153q2139 3057);"/>
                    <Edge cubics="!2140 2958(;2144,2958 2148,2958 2151,2958q2140 2958Q2146 2958q2151 2958);"/>
                    <Edge cubics="!1674 3908(;1671,3913 1667,3919 1664,3925q1674 3908Q1669 3916q1664 3925);"/>
                    <Edge cubics="!1593 3908(;1588,3903 1583,3896 1580,3888q1593 3908Q1585 3900q1580 3888);"/>
                    <Edge cubics="!1451 4020(;1507,3979 1554,3941 1593,3908q1451 4020Q1535 3958q1593 3908);"/>
                    <Edge cubics="!1619 3924(;1628,3913 1636,3902 1643,3891q1619 3924Q1633 3907q1643 3891);"/>
                    <Edge cubics="!1664 3925(;1595,4028 1464,4155 1271,4306q1664 3925Q1560 4080q1271 4306);"/>
                    <Edge cubics="!1122 4365(;1374,4170 1540,4023 1619,3924q1122 4365Q1500 4073q1619 3924);"/>
                    <Edge cubics="!1229 4176(;1330,4107 1404,4055 1451,4020q1229 4176Q1380 4072q1451 4020);"/>
                    <Edge cubics="!968 4486(;1013,4450 1064,4410 1122,4365q968 4486Q1035 4432q1122 4365);"/>
                    <Edge cubics="!1271 4306(;1200,4362 1105,4433 987,4520q1271 4306Q1164 4390q987 4520);"/>
                    <Edge cubics="!2526 3945(;2531,3951 2535,3957 2540,3963q2526 3945Q2533 3954q2540 3963);"/>
                    <Edge cubics="!2443 4132(;2336,4027 2282,3946 2282,3888q2443 4132Q2282 3975q2282 3888);"/>
                    <Edge cubics="!2007 4071(;2007,4072 2007,4074 2007,4076q2007 4071Q2007 4073q2007 4076);"/>
                    <Edge cubics="!1984 4047(;1985,4045 1985,4043 1986,4041q1984 4047Q1985 4044q1986 4041);"/>
                    <Edge cubics="!1875 3994(;1864,4021 1853,4047 1841,4073q1875 3994Q1859 4034q1841 4073);"/>
                    <Edge cubics="!1836 3995(;1840,3986 1844,3977 1847,3968q1836 3995Q1842 3982q1847 3968);"/>
                    <Edge cubics="!2007 4076(;2007,4173 1999,4256 1983,4327q2007 4076Q2007 4221q1983 4327);"/>
                    <Edge cubics="!1933 4263(;1952,4174 1969,4102 1984,4047q1933 4263Q1961 4130q1984 4047);"/>
                    <Edge cubics="!1983 4327(;1966,4399 1958,4453 1958,4489q1983 4327Q1958 4435q1958 4489);"/>
                    <Edge cubics="!2323 3873(;2355,3929 2421,4002 2522,4091q2323 3873Q2371 3957q2522 4091);"/>
                    <Edge cubics="!1804 3657(;1761,3754 1718,3837 1674,3908q1804 3657Q1740 3802q1674 3908);"/>
                    <Edge cubics="!1643 3891(;1666,3856 1690,3814 1714,3766q1643 3891Q1678 3838q1714 3766);"/>
                    <Edge cubics="!1714 3766(;1750,3695 1787,3611 1824,3512q1714 3766Q1768 3660q1824 3512);"/>
                    <Edge cubics="!1580 3888(;1574,3861 1571,3848 1571,3847q1580 3888Q1571 3848q1571 3847);"/>
                    <Edge cubics="!2012 3388(;1993,3608 1947,3810 1875,3994q2012 3388Q1983 3718q1875 3994);"/>
                    <Edge cubics="!1847 3968(;1870,3911 1890,3851 1907,3790q1847 3968Q1882 3882q1907 3790);"/>
                    <Edge cubics="!2268 3464(;2328,3644 2414,3804 2526,3945q2268 3464Q2358 3734q2526 3945);"/>
                    <Edge cubics="!2567 4043(;2562,4039 2558,4035 2553,4032q2567 4043Q2560 4037q2553 4032);"/>
                    <Edge cubics="!2700 4320(;2667,4307 2632,4287 2594,4260q2700 4320Q2651 4301q2594 4260);"/>
                    <Edge cubics="!2597 4156(;2600,4158 2603,4160 2606,4163q2597 4156Q2601 4159q2606 4163);"/>
                    <Edge cubics="!2606 4163(;2669,4215 2736,4266 2807,4316q2606 4163Q2700 4241q2807 4316);"/>
                    <Edge cubics="!2833 4274(;2744,4187 2656,4110 2567,4043q2833 4274Q2700 4144q2567 4043);"/>
                    <Edge cubics="!3015 4510(;3025,4521 3035,4531 3044,4541q3015 4510Q3030 4526q3044 4541);"/>
                    <Edge cubics="!3044 4541(;3134,4639 3199,4706 3239,4743q3044 4541Q3179 4688q3239 4743);"/>
                    <Edge cubics="!2807 4316(;2864,4356 2933,4421 3015,4510q2807 4316Q2892 4376q3015 4510);"/>
                    <Edge cubics="!3074 4518(;2969,4409 2888,4327 2833,4274q3074 4518Q2916 4354q2833 4274);"/>
                    <Edge cubics="!2197 2932(;2197,2913 2194,2899 2189,2891q2197 2932Q2197 2903q2189 2891);"/>
                    <Edge cubics="!2209 2889(;2212,2897 2213,2908 2213,2923q2209 2889Q2213 2901q2213 2923);"/>
                    <Edge cubics="!2553 4032(;2468,3968 2377,3817 2280,3579q2553 4032Q2426 3936q2280 3579);"/>
                    <Edge cubics="!1964 2901(;1999,2899 2028,2897 2049,2895q1964 2901Q2017 2898q2049 2895);"/>
                    <Edge cubics="!2522 4091(;2547,4113 2572,4135 2597,4156q2522 4091Q2559 4124q2597 4156);"/>
                    <Edge cubics="!2594 4260(;2548,4227 2498,4185 2443,4132q2594 4260Q2525 4211q2443 4132);"/>
                    <Edge cubics="!2050 2895(;2055,2895 2072,2898 2102,2905q2050 2895Q2057 2895q2102 2905);"/>
                    <Edge cubics="!3737 964(;3817,898 3927,810 4068,699q3737 964Q3857 865q4068 699);"/>
                    <Edge cubics="!4068 699(;4178,613 4306,514 4453,401q4068 699Q4233 570q4453 401);"/>
                    <Edge cubics="!614 971(;632,982 652,994 673,1007q614 971Q641 988q673 1007);"/>
                    <Edge cubics="!673 1007(;717,1033 778,1065 856,1102q673 1007Q739 1046q856 1102);"/>
                    <Edge cubics="!487 4876(;496,4857 507,4842 519,4829q487 4876Q501 4848q519 4829);"/>
                    <Edge cubics="!519 4829(;519,4829 519,4828 519,4828q519 4829 519 4828);"/>
                    <Edge cubics="!506 873(;527,904 563,936 614,971q506 873Q538 919q614 971);"/>
                    <Edge cubics="!1651 5174(;1600,5241 1545,5302 1486,5358q1651 5174Q1575 5274q1486 5358);"/>
                    <Edge cubics="!1460 5355(;1487,5318 1538,5252 1612,5155q1460 5355Q1501 5300q1612 5155);"/>
                    <Edge cubics="!1486 5358(;1473,5369 1461,5381 1448,5392q1486 5358Q1467 5375q1448 5392);"/>
                    <Edge cubics="!1437 5386(;1439,5383 1447,5372 1460,5355q1437 5386Q1440 5381q1460 5355);"/>
                    <Edge cubics="!732 4689(;732,4677 811,4609 968,4486q732 4689Q732 4671q968 4486);"/>
                    <Edge cubics="!987 4520(;915,4573 834,4631 745,4695q987 4520Q879 4599q745 4695);"/>
                    <Edge cubics="!856 1102(;885,1116 917,1131 951,1147q856 1102Q900 1123q951 1147);"/>
                    <Edge cubics="!456 5004(;456,4960 466,4917 487,4876q456 5004Q456 4938q487 4876);"/>
                  </edges>
                </DOMShape>
              </elements>
            </DOMFrame>
          </frames>
        </DOMLayer>
      </layers>
    </DOMTimeline>
  </timeline>
</DOMSymbolItem>